{
    "AX(CDD)": {
        "error": 1.112208748186197e-22,
        "error_type": "SEM",
        "filter_outliers_dict": {
            "filter_outliers": true,
            "iterations": 1,
            "std_devs": 2
        },
        "fit": "average",
        "modifier_error": 3.490738598121102e-06,
        "modifier_value": 4.801071664290919e-06,
        "value": 4.801071664290918e-06
    },
    "H1": {
        "error": 0.0060304753286707525,
        "error_type": "SEM",
        "filter_outliers_dict": {
            "filter_outliers": true,
            "iterations": 1,
            "std_devs": 2
        },
        "fit": "average",
        "modifier_error": 0.0,
        "modifier_value": 0.0,
        "value": -0.002587315391624651
    },
    "H2": {
        "error": 0.01598435627016108,
        "error_type": "SEM",
        "filter_outliers_dict": {
            "filter_outliers": true,
            "iterations": 1,
            "std_devs": 2
        },
        "fit": "average",
        "modifier_error": 0.0,
        "modifier_value": 0.0,
        "value": -0.4406760312574504
    },
    "L1": {
        "error": 0.0072028359852940186,
        "error_type": "SEM",
        "filter_outliers_dict": {
            "filter_outliers": true,
            "iterations": 1,
            "std_devs": 2
        },
        "fit": "average",
        "modifier_error": 0.0,
        "modifier_value": 0.0,
        "value": -0.006065264406410576
    },
    "L2(CDD)": {
        "error": 3.472909805636999e-06,
        "error_type": "SEM",
        "filter_outliers_dict": {
            "filter_outliers": true,
            "iterations": 1,
            "std_devs": 10
        },
        "fit": "average",
        "modifier_error": 9.235626222562675e-07,
        "modifier_value": 3.360750165003643e-07,
        "value": 3.808984822137364e-06
    }
}